{
  "collectionName": "components_section_section_two_columns",
  "info": {
    "displayName": "Section Two Column",
    "description": ""
  },
  "options": {},
  "attributes": {
    "Headline": {
      "type": "text"
    },
    "Label": {
      "type": "string"
    },
    "sectionTwoColImage": {
      "type": "media",
      "multiple": false,
      "required": false,
      "allowedTypes": [
        "images",
        "files",
        "videos",
        "audios"
      ]
    },
    "styleType": {
      "type": "enumeration",
      "enum": [
        "Image Right",
        "Image Left"
      ]
    },
    "body": {
      "type": "customField",
      "options": {
        "preset": "standard"
      },
      "customField": "plugin::ckeditor.CKEditor"
    },
    "background": {
      "type": "enumeration",
      "enum": [
        "Light",
        "Dark",
        "Light Gray",
        "Color"
      ],
      "default": "Light"
    },
    "imageCol": {
      "type": "component",
      "repeatable": false,
      "component": "sub-section.image-col"
    }
  }
}
